{
  "version": "6",
  "dialect": "sqlite",
  "id": "1f59cfc4-e4b7-4f7e-9149-156975a441b4",
  "prevId": "4782360d-6875-4d98-a897-e874f3e2271c",
  "tables": {
    "cached_models": {
      "name": "cached_models",
      "columns": {
        "id": {
          "name": "id",
          "type": "text",
          "primaryKey": true,
          "notNull": true,
          "autoincrement": false
        },
        "provider_profile_id": {
          "name": "provider_profile_id",
          "type": "text",
          "primaryKey": false,
          "notNull": true,
          "autoincrement": false
        },
        "model_slug": {
          "name": "model_slug",
          "type": "text",
          "primaryKey": false,
          "notNull": true,
          "autoincrement": false
        },
        "model_name": {
          "name": "model_name",
          "type": "text",
          "primaryKey": false,
          "notNull": true,
          "autoincrement": false
        },
        "context_length": {
          "name": "context_length",
          "type": "integer",
          "primaryKey": false,
          "notNull": false,
          "autoincrement": false
        },
        "capabilities_json": {
          "name": "capabilities_json",
          "type": "text",
          "primaryKey": false,
          "notNull": true,
          "autoincrement": false,
          "default": "'{}'"
        },
        "fetched_at": {
          "name": "fetched_at",
          "type": "text",
          "primaryKey": false,
          "notNull": true,
          "autoincrement": false
        }
      },
      "indexes": {
        "idx_cached_models_provider_slug": {
          "name": "idx_cached_models_provider_slug",
          "columns": [
            "provider_profile_id",
            "model_slug"
          ],
          "isUnique": true
        }
      },
      "foreignKeys": {
        "cached_models_provider_profile_id_provider_profiles_id_fk": {
          "name": "cached_models_provider_profile_id_provider_profiles_id_fk",
          "tableFrom": "cached_models",
          "tableTo": "provider_profiles",
          "columnsFrom": [
            "provider_profile_id"
          ],
          "columnsTo": [
            "id"
          ],
          "onDelete": "cascade",
          "onUpdate": "no action"
        }
      },
      "compositePrimaryKeys": {},
      "uniqueConstraints": {},
      "checkConstraints": {}
    },
    "characters": {
      "name": "characters",
      "columns": {
        "id": {
          "name": "id",
          "type": "text",
          "primaryKey": true,
          "notNull": true,
          "autoincrement": false
        },
        "name": {
          "name": "name",
          "type": "text",
          "primaryKey": false,
          "notNull": true,
          "autoincrement": false
        },
        "is_system": {
          "name": "is_system",
          "type": "integer",
          "primaryKey": false,
          "notNull": true,
          "autoincrement": false,
          "default": 0
        },
        "description": {
          "name": "description",
          "type": "text",
          "primaryKey": false,
          "notNull": true,
          "autoincrement": false,
          "default": "''"
        },
        "personality_summary": {
          "name": "personality_summary",
          "type": "text",
          "primaryKey": false,
          "notNull": false,
          "autoincrement": false
        },
        "default_scenario": {
          "name": "default_scenario",
          "type": "text",
          "primaryKey": false,
          "notNull": false,
          "autoincrement": false
        },
        "first_message": {
          "name": "first_message",
          "type": "text",
          "primaryKey": false,
          "notNull": false,
          "autoincrement": false
        },
        "mes_example": {
          "name": "mes_example",
          "type": "text",
          "primaryKey": false,
          "notNull": false,
          "autoincrement": false
        },
        "alternate_greetings_json": {
          "name": "alternate_greetings_json",
          "type": "text",
          "primaryKey": false,
          "notNull": true,
          "autoincrement": false,
          "default": "'[]'"
        },
        "post_history_instructions": {
          "name": "post_history_instructions",
          "type": "text",
          "primaryKey": false,
          "notNull": false,
          "autoincrement": false
        },
        "creator_notes": {
          "name": "creator_notes",
          "type": "text",
          "primaryKey": false,
          "notNull": false,
          "autoincrement": false
        },
        "character_book_json": {
          "name": "character_book_json",
          "type": "text",
          "primaryKey": false,
          "notNull": false,
          "autoincrement": false
        },
        "depth_prompt": {
          "name": "depth_prompt",
          "type": "text",
          "primaryKey": false,
          "notNull": false,
          "autoincrement": false
        },
        "depth_prompt_depth": {
          "name": "depth_prompt_depth",
          "type": "integer",
          "primaryKey": false,
          "notNull": false,
          "autoincrement": false
        },
        "depth_prompt_role": {
          "name": "depth_prompt_role",
          "type": "text",
          "primaryKey": false,
          "notNull": false,
          "autoincrement": false
        },
        "extensions_json": {
          "name": "extensions_json",
          "type": "text",
          "primaryKey": false,
          "notNull": true,
          "autoincrement": false,
          "default": "'{}'"
        },
        "system_prompt": {
          "name": "system_prompt",
          "type": "text",
          "primaryKey": false,
          "notNull": false,
          "autoincrement": false
        },
        "tags_json": {
          "name": "tags_json",
          "type": "text",
          "primaryKey": false,
          "notNull": true,
          "autoincrement": false,
          "default": "'[]'"
        },
        "avatar_asset_id": {
          "name": "avatar_asset_id",
          "type": "text",
          "primaryKey": false,
          "notNull": false,
          "autoincrement": false
        },
        "avatar_full_asset_id": {
          "name": "avatar_full_asset_id",
          "type": "text",
          "primaryKey": false,
          "notNull": false,
          "autoincrement": false
        },
        "mes_example_mode": {
          "name": "mes_example_mode",
          "type": "text",
          "primaryKey": false,
          "notNull": true,
          "autoincrement": false,
          "default": "'always'"
        },
        "mes_example_depth": {
          "name": "mes_example_depth",
          "type": "integer",
          "primaryKey": false,
          "notNull": true,
          "autoincrement": false,
          "default": 4
        },
        "status": {
          "name": "status",
          "type": "text",
          "primaryKey": false,
          "notNull": true,
          "autoincrement": false,
          "default": "'active'"
        },
        "created_at": {
          "name": "created_at",
          "type": "text",
          "primaryKey": false,
          "notNull": true,
          "autoincrement": false
        },
        "updated_at": {
          "name": "updated_at",
          "type": "text",
          "primaryKey": false,
          "notNull": true,
          "autoincrement": false
        }
      },
      "indexes": {},
      "foreignKeys": {},
      "compositePrimaryKeys": {},
      "uniqueConstraints": {},
      "checkConstraints": {}
    },
    "chat_branches": {
      "name": "chat_branches",
      "columns": {
        "id": {
          "name": "id",
          "type": "text",
          "primaryKey": true,
          "notNull": true,
          "autoincrement": false
        },
        "chat_id": {
          "name": "chat_id",
          "type": "text",
          "primaryKey": false,
          "notNull": true,
          "autoincrement": false
        },
        "parent_branch_id": {
          "name": "parent_branch_id",
          "type": "text",
          "primaryKey": false,
          "notNull": false,
          "autoincrement": false
        },
        "forked_from_message_id": {
          "name": "forked_from_message_id",
          "type": "text",
          "primaryKey": false,
          "notNull": false,
          "autoincrement": false
        },
        "label": {
          "name": "label",
          "type": "text",
          "primaryKey": false,
          "notNull": true,
          "autoincrement": false
        },
        "created_at": {
          "name": "created_at",
          "type": "text",
          "primaryKey": false,
          "notNull": true,
          "autoincrement": false
        }
      },
      "indexes": {
        "idx_chat_branches_chat_id": {
          "name": "idx_chat_branches_chat_id",
          "columns": [
            "chat_id"
          ],
          "isUnique": false
        }
      },
      "foreignKeys": {
        "chat_branches_chat_id_chats_id_fk": {
          "name": "chat_branches_chat_id_chats_id_fk",
          "tableFrom": "chat_branches",
          "tableTo": "chats",
          "columnsFrom": [
            "chat_id"
          ],
          "columnsTo": [
            "id"
          ],
          "onDelete": "cascade",
          "onUpdate": "no action"
        }
      },
      "compositePrimaryKeys": {},
      "uniqueConstraints": {},
      "checkConstraints": {}
    },
    "chats": {
      "name": "chats",
      "columns": {
        "id": {
          "name": "id",
          "type": "text",
          "primaryKey": true,
          "notNull": true,
          "autoincrement": false
        },
        "character_id": {
          "name": "character_id",
          "type": "text",
          "primaryKey": false,
          "notNull": true,
          "autoincrement": false
        },
        "persona_id": {
          "name": "persona_id",
          "type": "text",
          "primaryKey": false,
          "notNull": false,
          "autoincrement": false
        },
        "active_branch_id": {
          "name": "active_branch_id",
          "type": "text",
          "primaryKey": false,
          "notNull": true,
          "autoincrement": false
        },
        "prompt_preset_id": {
          "name": "prompt_preset_id",
          "type": "text",
          "primaryKey": false,
          "notNull": true,
          "autoincrement": false
        },
        "title": {
          "name": "title",
          "type": "text",
          "primaryKey": false,
          "notNull": true,
          "autoincrement": false
        },
        "summary": {
          "name": "summary",
          "type": "text",
          "primaryKey": false,
          "notNull": true,
          "autoincrement": false,
          "default": "''"
        },
        "message_history_limit": {
          "name": "message_history_limit",
          "type": "integer",
          "primaryKey": false,
          "notNull": true,
          "autoincrement": false,
          "default": 0
        },
        "last_accessed_at": {
          "name": "last_accessed_at",
          "type": "text",
          "primaryKey": false,
          "notNull": true,
          "autoincrement": false,
          "default": "''"
        },
        "status": {
          "name": "status",
          "type": "text",
          "primaryKey": false,
          "notNull": true,
          "autoincrement": false,
          "default": "'active'"
        },
        "created_at": {
          "name": "created_at",
          "type": "text",
          "primaryKey": false,
          "notNull": true,
          "autoincrement": false
        },
        "updated_at": {
          "name": "updated_at",
          "type": "text",
          "primaryKey": false,
          "notNull": true,
          "autoincrement": false
        },
        "lore_activation_state_json": {
          "name": "lore_activation_state_json",
          "type": "text",
          "primaryKey": false,
          "notNull": true,
          "autoincrement": false,
          "default": "'{}'"
        },
        "script_state_json": {
          "name": "script_state_json",
          "type": "text",
          "primaryKey": false,
          "notNull": true,
          "autoincrement": false,
          "default": "'{}'"
        }
      },
      "indexes": {
        "idx_chats_character_id": {
          "name": "idx_chats_character_id",
          "columns": [
            "character_id"
          ],
          "isUnique": false
        },
        "idx_chats_last_accessed": {
          "name": "idx_chats_last_accessed",
          "columns": [
            "last_accessed_at"
          ],
          "isUnique": false
        }
      },
      "foreignKeys": {
        "chats_character_id_characters_id_fk": {
          "name": "chats_character_id_characters_id_fk",
          "tableFrom": "chats",
          "tableTo": "characters",
          "columnsFrom": [
            "character_id"
          ],
          "columnsTo": [
            "id"
          ],
          "onDelete": "cascade",
          "onUpdate": "no action"
        },
        "chats_persona_id_personas_id_fk": {
          "name": "chats_persona_id_personas_id_fk",
          "tableFrom": "chats",
          "tableTo": "personas",
          "columnsFrom": [
            "persona_id"
          ],
          "columnsTo": [
            "id"
          ],
          "onDelete": "set null",
          "onUpdate": "no action"
        },
        "chats_prompt_preset_id_prompt_presets_id_fk": {
          "name": "chats_prompt_preset_id_prompt_presets_id_fk",
          "tableFrom": "chats",
          "tableTo": "prompt_presets",
          "columnsFrom": [
            "prompt_preset_id"
          ],
          "columnsTo": [
            "id"
          ],
          "onDelete": "no action",
          "onUpdate": "no action"
        }
      },
      "compositePrimaryKeys": {},
      "uniqueConstraints": {},
      "checkConstraints": {}
    },
    "lore_entries": {
      "name": "lore_entries",
      "columns": {
        "id": {
          "name": "id",
          "type": "text",
          "primaryKey": true,
          "notNull": true,
          "autoincrement": false
        },
        "lorebook_id": {
          "name": "lorebook_id",
          "type": "text",
          "primaryKey": false,
          "notNull": true,
          "autoincrement": false
        },
        "title": {
          "name": "title",
          "type": "text",
          "primaryKey": false,
          "notNull": true,
          "autoincrement": false,
          "default": "''"
        },
        "content": {
          "name": "content",
          "type": "text",
          "primaryKey": false,
          "notNull": true,
          "autoincrement": false,
          "default": "''"
        },
        "keys_json": {
          "name": "keys_json",
          "type": "text",
          "primaryKey": false,
          "notNull": true,
          "autoincrement": false,
          "default": "'[]'"
        },
        "secondary_keys_json": {
          "name": "secondary_keys_json",
          "type": "text",
          "primaryKey": false,
          "notNull": true,
          "autoincrement": false,
          "default": "'[]'"
        },
        "logic": {
          "name": "logic",
          "type": "text",
          "primaryKey": false,
          "notNull": true,
          "autoincrement": false,
          "default": "'and_any'"
        },
        "position": {
          "name": "position",
          "type": "text",
          "primaryKey": false,
          "notNull": true,
          "autoincrement": false,
          "default": "'in_prompt'"
        },
        "depth": {
          "name": "depth",
          "type": "integer",
          "primaryKey": false,
          "notNull": true,
          "autoincrement": false,
          "default": 4
        },
        "priority": {
          "name": "priority",
          "type": "integer",
          "primaryKey": false,
          "notNull": true,
          "autoincrement": false,
          "default": 100
        },
        "sticky_window": {
          "name": "sticky_window",
          "type": "integer",
          "primaryKey": false,
          "notNull": true,
          "autoincrement": false,
          "default": 0
        },
        "cooldown_window": {
          "name": "cooldown_window",
          "type": "integer",
          "primaryKey": false,
          "notNull": true,
          "autoincrement": false,
          "default": 0
        },
        "delay_window": {
          "name": "delay_window",
          "type": "integer",
          "primaryKey": false,
          "notNull": true,
          "autoincrement": false,
          "default": 0
        },
        "constant": {
          "name": "constant",
          "type": "integer",
          "primaryKey": false,
          "notNull": true,
          "autoincrement": false,
          "default": 0
        },
        "probability": {
          "name": "probability",
          "type": "integer",
          "primaryKey": false,
          "notNull": true,
          "autoincrement": false,
          "default": 100
        },
        "role": {
          "name": "role",
          "type": "text",
          "primaryKey": false,
          "notNull": true,
          "autoincrement": false,
          "default": "'system'"
        },
        "group_name": {
          "name": "group_name",
          "type": "text",
          "primaryKey": false,
          "notNull": true,
          "autoincrement": false,
          "default": "''"
        },
        "group_weight": {
          "name": "group_weight",
          "type": "integer",
          "primaryKey": false,
          "notNull": true,
          "autoincrement": false,
          "default": 100
        },
        "prioritize_inclusion": {
          "name": "prioritize_inclusion",
          "type": "integer",
          "primaryKey": false,
          "notNull": true,
          "autoincrement": false,
          "default": 0
        },
        "exclude_recursion": {
          "name": "exclude_recursion",
          "type": "integer",
          "primaryKey": false,
          "notNull": true,
          "autoincrement": false,
          "default": 0
        },
        "prevent_recursion": {
          "name": "prevent_recursion",
          "type": "integer",
          "primaryKey": false,
          "notNull": true,
          "autoincrement": false,
          "default": 0
        },
        "delay_until_recursion": {
          "name": "delay_until_recursion",
          "type": "integer",
          "primaryKey": false,
          "notNull": true,
          "autoincrement": false,
          "default": 0
        },
        "recursion_level": {
          "name": "recursion_level",
          "type": "integer",
          "primaryKey": false,
          "notNull": true,
          "autoincrement": false,
          "default": 0
        },
        "scan_depth_override": {
          "name": "scan_depth_override",
          "type": "integer",
          "primaryKey": false,
          "notNull": false,
          "autoincrement": false
        },
        "case_sensitive": {
          "name": "case_sensitive",
          "type": "integer",
          "primaryKey": false,
          "notNull": true,
          "autoincrement": false,
          "default": 0
        },
        "match_whole_words": {
          "name": "match_whole_words",
          "type": "integer",
          "primaryKey": false,
          "notNull": true,
          "autoincrement": false,
          "default": 0
        },
        "character_filter_json": {
          "name": "character_filter_json",
          "type": "text",
          "primaryKey": false,
          "notNull": true,
          "autoincrement": false,
          "default": "'[]'"
        },
        "character_filter_exclude": {
          "name": "character_filter_exclude",
          "type": "integer",
          "primaryKey": false,
          "notNull": true,
          "autoincrement": false,
          "default": 0
        },
        "triggers_json": {
          "name": "triggers_json",
          "type": "text",
          "primaryKey": false,
          "notNull": true,
          "autoincrement": false,
          "default": "'[]'"
        },
        "match_sources_json": {
          "name": "match_sources_json",
          "type": "text",
          "primaryKey": false,
          "notNull": true,
          "autoincrement": false,
          "default": "'[]'"
        },
        "enabled": {
          "name": "enabled",
          "type": "integer",
          "primaryKey": false,
          "notNull": true,
          "autoincrement": false,
          "default": 1
        },
        "sort_order": {
          "name": "sort_order",
          "type": "integer",
          "primaryKey": false,
          "notNull": true,
          "autoincrement": false,
          "default": 0
        },
        "metadata_json": {
          "name": "metadata_json",
          "type": "text",
          "primaryKey": false,
          "notNull": true,
          "autoincrement": false,
          "default": "'{}'"
        },
        "created_at": {
          "name": "created_at",
          "type": "text",
          "primaryKey": false,
          "notNull": true,
          "autoincrement": false
        },
        "updated_at": {
          "name": "updated_at",
          "type": "text",
          "primaryKey": false,
          "notNull": true,
          "autoincrement": false
        }
      },
      "indexes": {
        "idx_lore_entries_lorebook": {
          "name": "idx_lore_entries_lorebook",
          "columns": [
            "lorebook_id"
          ],
          "isUnique": false
        }
      },
      "foreignKeys": {
        "lore_entries_lorebook_id_lorebooks_id_fk": {
          "name": "lore_entries_lorebook_id_lorebooks_id_fk",
          "tableFrom": "lore_entries",
          "tableTo": "lorebooks",
          "columnsFrom": [
            "lorebook_id"
          ],
          "columnsTo": [
            "id"
          ],
          "onDelete": "cascade",
          "onUpdate": "no action"
        }
      },
      "compositePrimaryKeys": {},
      "uniqueConstraints": {},
      "checkConstraints": {}
    },
    "lorebooks": {
      "name": "lorebooks",
      "columns": {
        "id": {
          "name": "id",
          "type": "text",
          "primaryKey": true,
          "notNull": true,
          "autoincrement": false
        },
        "name": {
          "name": "name",
          "type": "text",
          "primaryKey": false,
          "notNull": true,
          "autoincrement": false
        },
        "description": {
          "name": "description",
          "type": "text",
          "primaryKey": false,
          "notNull": true,
          "autoincrement": false,
          "default": "''"
        },
        "scope_type": {
          "name": "scope_type",
          "type": "text",
          "primaryKey": false,
          "notNull": true,
          "autoincrement": false
        },
        "scan_depth": {
          "name": "scan_depth",
          "type": "integer",
          "primaryKey": false,
          "notNull": true,
          "autoincrement": false,
          "default": 50
        },
        "token_budget": {
          "name": "token_budget",
          "type": "integer",
          "primaryKey": false,
          "notNull": true,
          "autoincrement": false,
          "default": 1000
        },
        "recursive_scanning": {
          "name": "recursive_scanning",
          "type": "integer",
          "primaryKey": false,
          "notNull": true,
          "autoincrement": false,
          "default": 0
        },
        "sort_order": {
          "name": "sort_order",
          "type": "integer",
          "primaryKey": false,
          "notNull": true,
          "autoincrement": false,
          "default": 0
        },
        "character_id": {
          "name": "character_id",
          "type": "text",
          "primaryKey": false,
          "notNull": false,
          "autoincrement": false
        },
        "persona_id": {
          "name": "persona_id",
          "type": "text",
          "primaryKey": false,
          "notNull": false,
          "autoincrement": false
        },
        "chat_id": {
          "name": "chat_id",
          "type": "text",
          "primaryKey": false,
          "notNull": false,
          "autoincrement": false
        },
        "extensions_json": {
          "name": "extensions_json",
          "type": "text",
          "primaryKey": false,
          "notNull": true,
          "autoincrement": false,
          "default": "'{}'"
        },
        "created_at": {
          "name": "created_at",
          "type": "text",
          "primaryKey": false,
          "notNull": true,
          "autoincrement": false
        },
        "updated_at": {
          "name": "updated_at",
          "type": "text",
          "primaryKey": false,
          "notNull": true,
          "autoincrement": false
        }
      },
      "indexes": {
        "idx_lorebooks_character": {
          "name": "idx_lorebooks_character",
          "columns": [
            "character_id"
          ],
          "isUnique": false
        },
        "idx_lorebooks_persona": {
          "name": "idx_lorebooks_persona",
          "columns": [
            "persona_id"
          ],
          "isUnique": false
        },
        "idx_lorebooks_chat": {
          "name": "idx_lorebooks_chat",
          "columns": [
            "chat_id"
          ],
          "isUnique": false
        },
        "idx_lorebooks_scope": {
          "name": "idx_lorebooks_scope",
          "columns": [
            "scope_type"
          ],
          "isUnique": false
        }
      },
      "foreignKeys": {
        "lorebooks_character_id_characters_id_fk": {
          "name": "lorebooks_character_id_characters_id_fk",
          "tableFrom": "lorebooks",
          "tableTo": "characters",
          "columnsFrom": [
            "character_id"
          ],
          "columnsTo": [
            "id"
          ],
          "onDelete": "cascade",
          "onUpdate": "no action"
        },
        "lorebooks_persona_id_personas_id_fk": {
          "name": "lorebooks_persona_id_personas_id_fk",
          "tableFrom": "lorebooks",
          "tableTo": "personas",
          "columnsFrom": [
            "persona_id"
          ],
          "columnsTo": [
            "id"
          ],
          "onDelete": "cascade",
          "onUpdate": "no action"
        },
        "lorebooks_chat_id_chats_id_fk": {
          "name": "lorebooks_chat_id_chats_id_fk",
          "tableFrom": "lorebooks",
          "tableTo": "chats",
          "columnsFrom": [
            "chat_id"
          ],
          "columnsTo": [
            "id"
          ],
          "onDelete": "cascade",
          "onUpdate": "no action"
        }
      },
      "compositePrimaryKeys": {},
      "uniqueConstraints": {},
      "checkConstraints": {}
    },
    "message_variants": {
      "name": "message_variants",
      "columns": {
        "id": {
          "name": "id",
          "type": "text",
          "primaryKey": true,
          "notNull": true,
          "autoincrement": false
        },
        "message_id": {
          "name": "message_id",
          "type": "text",
          "primaryKey": false,
          "notNull": true,
          "autoincrement": false
        },
        "variant_index": {
          "name": "variant_index",
          "type": "integer",
          "primaryKey": false,
          "notNull": true,
          "autoincrement": false
        },
        "content": {
          "name": "content",
          "type": "text",
          "primaryKey": false,
          "notNull": true,
          "autoincrement": false
        },
        "is_selected": {
          "name": "is_selected",
          "type": "integer",
          "primaryKey": false,
          "notNull": true,
          "autoincrement": false,
          "default": 0
        },
        "finish_reason": {
          "name": "finish_reason",
          "type": "text",
          "primaryKey": false,
          "notNull": false,
          "autoincrement": false
        },
        "reasoning": {
          "name": "reasoning",
          "type": "text",
          "primaryKey": false,
          "notNull": false,
          "autoincrement": false
        },
        "reasoning_duration_ms": {
          "name": "reasoning_duration_ms",
          "type": "integer",
          "primaryKey": false,
          "notNull": false,
          "autoincrement": false
        },
        "created_at": {
          "name": "created_at",
          "type": "text",
          "primaryKey": false,
          "notNull": true,
          "autoincrement": false
        }
      },
      "indexes": {
        "idx_message_variants_unique": {
          "name": "idx_message_variants_unique",
          "columns": [
            "message_id",
            "variant_index"
          ],
          "isUnique": true
        }
      },
      "foreignKeys": {
        "message_variants_message_id_messages_id_fk": {
          "name": "message_variants_message_id_messages_id_fk",
          "tableFrom": "message_variants",
          "tableTo": "messages",
          "columnsFrom": [
            "message_id"
          ],
          "columnsTo": [
            "id"
          ],
          "onDelete": "cascade",
          "onUpdate": "no action"
        }
      },
      "compositePrimaryKeys": {},
      "uniqueConstraints": {},
      "checkConstraints": {}
    },
    "messages": {
      "name": "messages",
      "columns": {
        "id": {
          "name": "id",
          "type": "text",
          "primaryKey": true,
          "notNull": true,
          "autoincrement": false
        },
        "chat_id": {
          "name": "chat_id",
          "type": "text",
          "primaryKey": false,
          "notNull": true,
          "autoincrement": false
        },
        "branch_id": {
          "name": "branch_id",
          "type": "text",
          "primaryKey": false,
          "notNull": true,
          "autoincrement": false
        },
        "role": {
          "name": "role",
          "type": "text",
          "primaryKey": false,
          "notNull": true,
          "autoincrement": false
        },
        "author_type": {
          "name": "author_type",
          "type": "text",
          "primaryKey": false,
          "notNull": true,
          "autoincrement": false
        },
        "position": {
          "name": "position",
          "type": "integer",
          "primaryKey": false,
          "notNull": true,
          "autoincrement": false
        },
        "content": {
          "name": "content",
          "type": "text",
          "primaryKey": false,
          "notNull": true,
          "autoincrement": false
        },
        "state": {
          "name": "state",
          "type": "text",
          "primaryKey": false,
          "notNull": true,
          "autoincrement": false
        },
        "created_at": {
          "name": "created_at",
          "type": "text",
          "primaryKey": false,
          "notNull": true,
          "autoincrement": false
        },
        "updated_at": {
          "name": "updated_at",
          "type": "text",
          "primaryKey": false,
          "notNull": true,
          "autoincrement": false
        }
      },
      "indexes": {
        "idx_messages_branch_position": {
          "name": "idx_messages_branch_position",
          "columns": [
            "branch_id",
            "position"
          ],
          "isUnique": true
        }
      },
      "foreignKeys": {
        "messages_chat_id_chats_id_fk": {
          "name": "messages_chat_id_chats_id_fk",
          "tableFrom": "messages",
          "tableTo": "chats",
          "columnsFrom": [
            "chat_id"
          ],
          "columnsTo": [
            "id"
          ],
          "onDelete": "cascade",
          "onUpdate": "no action"
        },
        "messages_branch_id_chat_branches_id_fk": {
          "name": "messages_branch_id_chat_branches_id_fk",
          "tableFrom": "messages",
          "tableTo": "chat_branches",
          "columnsFrom": [
            "branch_id"
          ],
          "columnsTo": [
            "id"
          ],
          "onDelete": "cascade",
          "onUpdate": "no action"
        }
      },
      "compositePrimaryKeys": {},
      "uniqueConstraints": {},
      "checkConstraints": {}
    },
    "personas": {
      "name": "personas",
      "columns": {
        "id": {
          "name": "id",
          "type": "text",
          "primaryKey": true,
          "notNull": true,
          "autoincrement": false
        },
        "name": {
          "name": "name",
          "type": "text",
          "primaryKey": false,
          "notNull": true,
          "autoincrement": false
        },
        "description": {
          "name": "description",
          "type": "text",
          "primaryKey": false,
          "notNull": true,
          "autoincrement": false,
          "default": "''"
        },
        "pronouns": {
          "name": "pronouns",
          "type": "text",
          "primaryKey": false,
          "notNull": false,
          "autoincrement": false
        },
        "avatar_asset_id": {
          "name": "avatar_asset_id",
          "type": "text",
          "primaryKey": false,
          "notNull": false,
          "autoincrement": false
        },
        "avatar_full_asset_id": {
          "name": "avatar_full_asset_id",
          "type": "text",
          "primaryKey": false,
          "notNull": false,
          "autoincrement": false
        },
        "default_for_new_chats": {
          "name": "default_for_new_chats",
          "type": "integer",
          "primaryKey": false,
          "notNull": true,
          "autoincrement": false,
          "default": 0
        },
        "created_at": {
          "name": "created_at",
          "type": "text",
          "primaryKey": false,
          "notNull": true,
          "autoincrement": false
        },
        "updated_at": {
          "name": "updated_at",
          "type": "text",
          "primaryKey": false,
          "notNull": true,
          "autoincrement": false
        }
      },
      "indexes": {},
      "foreignKeys": {},
      "compositePrimaryKeys": {},
      "uniqueConstraints": {},
      "checkConstraints": {}
    },
    "prompt_presets": {
      "name": "prompt_presets",
      "columns": {
        "id": {
          "name": "id",
          "type": "text",
          "primaryKey": true,
          "notNull": true,
          "autoincrement": false
        },
        "name": {
          "name": "name",
          "type": "text",
          "primaryKey": false,
          "notNull": true,
          "autoincrement": false
        },
        "bind_provider_preset_id": {
          "name": "bind_provider_preset_id",
          "type": "text",
          "primaryKey": false,
          "notNull": false,
          "autoincrement": false
        },
        "system_prompt": {
          "name": "system_prompt",
          "type": "text",
          "primaryKey": false,
          "notNull": true,
          "autoincrement": false,
          "default": "''"
        },
        "post_history_instructions": {
          "name": "post_history_instructions",
          "type": "text",
          "primaryKey": false,
          "notNull": true,
          "autoincrement": false,
          "default": "''"
        },
        "assistant_prefix": {
          "name": "assistant_prefix",
          "type": "text",
          "primaryKey": false,
          "notNull": true,
          "autoincrement": false,
          "default": "''"
        },
        "authors_note": {
          "name": "authors_note",
          "type": "text",
          "primaryKey": false,
          "notNull": true,
          "autoincrement": false,
          "default": "''"
        },
        "authors_note_depth": {
          "name": "authors_note_depth",
          "type": "integer",
          "primaryKey": false,
          "notNull": true,
          "autoincrement": false,
          "default": 4
        },
        "summary_prompt": {
          "name": "summary_prompt",
          "type": "text",
          "primaryKey": false,
          "notNull": true,
          "autoincrement": false,
          "default": "''"
        },
        "tools_prompt": {
          "name": "tools_prompt",
          "type": "text",
          "primaryKey": false,
          "notNull": true,
          "autoincrement": false,
          "default": "''"
        },
        "created_at": {
          "name": "created_at",
          "type": "text",
          "primaryKey": false,
          "notNull": true,
          "autoincrement": false
        },
        "updated_at": {
          "name": "updated_at",
          "type": "text",
          "primaryKey": false,
          "notNull": true,
          "autoincrement": false
        }
      },
      "indexes": {},
      "foreignKeys": {
        "prompt_presets_bind_provider_preset_id_provider_profiles_id_fk": {
          "name": "prompt_presets_bind_provider_preset_id_provider_profiles_id_fk",
          "tableFrom": "prompt_presets",
          "tableTo": "provider_profiles",
          "columnsFrom": [
            "bind_provider_preset_id"
          ],
          "columnsTo": [
            "id"
          ],
          "onDelete": "set null",
          "onUpdate": "no action"
        }
      },
      "compositePrimaryKeys": {},
      "uniqueConstraints": {},
      "checkConstraints": {}
    },
    "prompt_traces": {
      "name": "prompt_traces",
      "columns": {
        "id": {
          "name": "id",
          "type": "text",
          "primaryKey": true,
          "notNull": true,
          "autoincrement": false
        },
        "chat_id": {
          "name": "chat_id",
          "type": "text",
          "primaryKey": false,
          "notNull": true,
          "autoincrement": false
        },
        "branch_id": {
          "name": "branch_id",
          "type": "text",
          "primaryKey": false,
          "notNull": true,
          "autoincrement": false
        },
        "message_id": {
          "name": "message_id",
          "type": "text",
          "primaryKey": false,
          "notNull": true,
          "autoincrement": false
        },
        "model": {
          "name": "model",
          "type": "text",
          "primaryKey": false,
          "notNull": true,
          "autoincrement": false
        },
        "preset_name": {
          "name": "preset_name",
          "type": "text",
          "primaryKey": false,
          "notNull": true,
          "autoincrement": false
        },
        "assembled_layers_json": {
          "name": "assembled_layers_json",
          "type": "text",
          "primaryKey": false,
          "notNull": true,
          "autoincrement": false
        },
        "token_accounting_json": {
          "name": "token_accounting_json",
          "type": "text",
          "primaryKey": false,
          "notNull": true,
          "autoincrement": false
        },
        "final_payload_json": {
          "name": "final_payload_json",
          "type": "text",
          "primaryKey": false,
          "notNull": true,
          "autoincrement": false,
          "default": "'{}'"
        },
        "prefill": {
          "name": "prefill",
          "type": "text",
          "primaryKey": false,
          "notNull": false,
          "autoincrement": false
        },
        "latency_ms": {
          "name": "latency_ms",
          "type": "integer",
          "primaryKey": false,
          "notNull": true,
          "autoincrement": false
        },
        "created_at": {
          "name": "created_at",
          "type": "text",
          "primaryKey": false,
          "notNull": true,
          "autoincrement": false
        }
      },
      "indexes": {
        "idx_prompt_traces_chat_branch": {
          "name": "idx_prompt_traces_chat_branch",
          "columns": [
            "chat_id",
            "branch_id",
            "created_at"
          ],
          "isUnique": false
        }
      },
      "foreignKeys": {
        "prompt_traces_chat_id_chats_id_fk": {
          "name": "prompt_traces_chat_id_chats_id_fk",
          "tableFrom": "prompt_traces",
          "tableTo": "chats",
          "columnsFrom": [
            "chat_id"
          ],
          "columnsTo": [
            "id"
          ],
          "onDelete": "cascade",
          "onUpdate": "no action"
        },
        "prompt_traces_branch_id_chat_branches_id_fk": {
          "name": "prompt_traces_branch_id_chat_branches_id_fk",
          "tableFrom": "prompt_traces",
          "tableTo": "chat_branches",
          "columnsFrom": [
            "branch_id"
          ],
          "columnsTo": [
            "id"
          ],
          "onDelete": "cascade",
          "onUpdate": "no action"
        },
        "prompt_traces_message_id_messages_id_fk": {
          "name": "prompt_traces_message_id_messages_id_fk",
          "tableFrom": "prompt_traces",
          "tableTo": "messages",
          "columnsFrom": [
            "message_id"
          ],
          "columnsTo": [
            "id"
          ],
          "onDelete": "cascade",
          "onUpdate": "no action"
        }
      },
      "compositePrimaryKeys": {},
      "uniqueConstraints": {},
      "checkConstraints": {}
    },
    "provider_model_favorites": {
      "name": "provider_model_favorites",
      "columns": {
        "id": {
          "name": "id",
          "type": "text",
          "primaryKey": true,
          "notNull": true,
          "autoincrement": false
        },
        "provider_profile_id": {
          "name": "provider_profile_id",
          "type": "text",
          "primaryKey": false,
          "notNull": true,
          "autoincrement": false
        },
        "model_id": {
          "name": "model_id",
          "type": "text",
          "primaryKey": false,
          "notNull": true,
          "autoincrement": false
        },
        "label": {
          "name": "label",
          "type": "text",
          "primaryKey": false,
          "notNull": false,
          "autoincrement": false
        },
        "context_length": {
          "name": "context_length",
          "type": "integer",
          "primaryKey": false,
          "notNull": false,
          "autoincrement": false
        },
        "created_at": {
          "name": "created_at",
          "type": "text",
          "primaryKey": false,
          "notNull": true,
          "autoincrement": false
        }
      },
      "indexes": {
        "idx_provider_model_favorites_unique": {
          "name": "idx_provider_model_favorites_unique",
          "columns": [
            "provider_profile_id",
            "model_id"
          ],
          "isUnique": true
        }
      },
      "foreignKeys": {
        "provider_model_favorites_provider_profile_id_provider_profiles_id_fk": {
          "name": "provider_model_favorites_provider_profile_id_provider_profiles_id_fk",
          "tableFrom": "provider_model_favorites",
          "tableTo": "provider_profiles",
          "columnsFrom": [
            "provider_profile_id"
          ],
          "columnsTo": [
            "id"
          ],
          "onDelete": "cascade",
          "onUpdate": "no action"
        }
      },
      "compositePrimaryKeys": {},
      "uniqueConstraints": {},
      "checkConstraints": {}
    },
    "provider_profiles": {
      "name": "provider_profiles",
      "columns": {
        "id": {
          "name": "id",
          "type": "text",
          "primaryKey": true,
          "notNull": true,
          "autoincrement": false
        },
        "name": {
          "name": "name",
          "type": "text",
          "primaryKey": false,
          "notNull": true,
          "autoincrement": false
        },
        "provider_preset": {
          "name": "provider_preset",
          "type": "text",
          "primaryKey": false,
          "notNull": true,
          "autoincrement": false
        },
        "endpoint": {
          "name": "endpoint",
          "type": "text",
          "primaryKey": false,
          "notNull": true,
          "autoincrement": false
        },
        "api_key": {
          "name": "api_key",
          "type": "text",
          "primaryKey": false,
          "notNull": false,
          "autoincrement": false
        },
        "default_model": {
          "name": "default_model",
          "type": "text",
          "primaryKey": false,
          "notNull": false,
          "autoincrement": false
        },
        "context_budget": {
          "name": "context_budget",
          "type": "integer",
          "primaryKey": false,
          "notNull": false,
          "autoincrement": false
        },
        "max_tokens": {
          "name": "max_tokens",
          "type": "integer",
          "primaryKey": false,
          "notNull": true,
          "autoincrement": false,
          "default": 2000
        },
        "temperature": {
          "name": "temperature",
          "type": "real",
          "primaryKey": false,
          "notNull": true,
          "autoincrement": false,
          "default": 1
        },
        "top_p": {
          "name": "top_p",
          "type": "real",
          "primaryKey": false,
          "notNull": true,
          "autoincrement": false,
          "default": 1
        },
        "top_k": {
          "name": "top_k",
          "type": "integer",
          "primaryKey": false,
          "notNull": true,
          "autoincrement": false,
          "default": 0
        },
        "min_p": {
          "name": "min_p",
          "type": "real",
          "primaryKey": false,
          "notNull": true,
          "autoincrement": false,
          "default": 0
        },
        "top_a": {
          "name": "top_a",
          "type": "real",
          "primaryKey": false,
          "notNull": true,
          "autoincrement": false,
          "default": 0
        },
        "frequency_penalty": {
          "name": "frequency_penalty",
          "type": "real",
          "primaryKey": false,
          "notNull": true,
          "autoincrement": false,
          "default": 0
        },
        "presence_penalty": {
          "name": "presence_penalty",
          "type": "real",
          "primaryKey": false,
          "notNull": true,
          "autoincrement": false,
          "default": 0
        },
        "repetition_penalty": {
          "name": "repetition_penalty",
          "type": "real",
          "primaryKey": false,
          "notNull": true,
          "autoincrement": false,
          "default": 1
        },
        "stop_sequences_json": {
          "name": "stop_sequences_json",
          "type": "text",
          "primaryKey": false,
          "notNull": false,
          "autoincrement": false
        },
        "seed": {
          "name": "seed",
          "type": "text",
          "primaryKey": false,
          "notNull": false,
          "autoincrement": false
        },
        "reasoning_effort": {
          "name": "reasoning_effort",
          "type": "text",
          "primaryKey": false,
          "notNull": true,
          "autoincrement": false,
          "default": "'auto'"
        },
        "show_reasoning": {
          "name": "show_reasoning",
          "type": "integer",
          "primaryKey": false,
          "notNull": true,
          "autoincrement": false,
          "default": 0
        },
        "stream_response": {
          "name": "stream_response",
          "type": "integer",
          "primaryKey": false,
          "notNull": true,
          "autoincrement": false,
          "default": 1
        },
        "custom_samplers": {
          "name": "custom_samplers",
          "type": "integer",
          "primaryKey": false,
          "notNull": true,
          "autoincrement": false,
          "default": 0
        },
        "is_active": {
          "name": "is_active",
          "type": "integer",
          "primaryKey": false,
          "notNull": true,
          "autoincrement": false,
          "default": 0
        },
        "created_at": {
          "name": "created_at",
          "type": "text",
          "primaryKey": false,
          "notNull": true,
          "autoincrement": false
        },
        "updated_at": {
          "name": "updated_at",
          "type": "text",
          "primaryKey": false,
          "notNull": true,
          "autoincrement": false
        }
      },
      "indexes": {},
      "foreignKeys": {},
      "compositePrimaryKeys": {},
      "uniqueConstraints": {},
      "checkConstraints": {}
    },
    "scripts": {
      "name": "scripts",
      "columns": {
        "id": {
          "name": "id",
          "type": "text",
          "primaryKey": true,
          "notNull": true,
          "autoincrement": false
        },
        "name": {
          "name": "name",
          "type": "text",
          "primaryKey": false,
          "notNull": true,
          "autoincrement": false
        },
        "description": {
          "name": "description",
          "type": "text",
          "primaryKey": false,
          "notNull": true,
          "autoincrement": false,
          "default": "''"
        },
        "code": {
          "name": "code",
          "type": "text",
          "primaryKey": false,
          "notNull": true,
          "autoincrement": false,
          "default": "''"
        },
        "enabled": {
          "name": "enabled",
          "type": "integer",
          "primaryKey": false,
          "notNull": true,
          "autoincrement": false,
          "default": 1
        },
        "scope_type": {
          "name": "scope_type",
          "type": "text",
          "primaryKey": false,
          "notNull": true,
          "autoincrement": false,
          "default": "'character'"
        },
        "sort_order": {
          "name": "sort_order",
          "type": "integer",
          "primaryKey": false,
          "notNull": true,
          "autoincrement": false,
          "default": 0
        },
        "character_id": {
          "name": "character_id",
          "type": "text",
          "primaryKey": false,
          "notNull": false,
          "autoincrement": false
        },
        "persona_id": {
          "name": "persona_id",
          "type": "text",
          "primaryKey": false,
          "notNull": false,
          "autoincrement": false
        },
        "chat_id": {
          "name": "chat_id",
          "type": "text",
          "primaryKey": false,
          "notNull": false,
          "autoincrement": false
        },
        "extensions_json": {
          "name": "extensions_json",
          "type": "text",
          "primaryKey": false,
          "notNull": true,
          "autoincrement": false,
          "default": "'{}'"
        },
        "created_at": {
          "name": "created_at",
          "type": "text",
          "primaryKey": false,
          "notNull": true,
          "autoincrement": false
        },
        "updated_at": {
          "name": "updated_at",
          "type": "text",
          "primaryKey": false,
          "notNull": true,
          "autoincrement": false
        }
      },
      "indexes": {
        "idx_scripts_character": {
          "name": "idx_scripts_character",
          "columns": [
            "character_id"
          ],
          "isUnique": false
        },
        "idx_scripts_persona": {
          "name": "idx_scripts_persona",
          "columns": [
            "persona_id"
          ],
          "isUnique": false
        },
        "idx_scripts_chat": {
          "name": "idx_scripts_chat",
          "columns": [
            "chat_id"
          ],
          "isUnique": false
        },
        "idx_scripts_scope": {
          "name": "idx_scripts_scope",
          "columns": [
            "scope_type"
          ],
          "isUnique": false
        }
      },
      "foreignKeys": {
        "scripts_character_id_characters_id_fk": {
          "name": "scripts_character_id_characters_id_fk",
          "tableFrom": "scripts",
          "tableTo": "characters",
          "columnsFrom": [
            "character_id"
          ],
          "columnsTo": [
            "id"
          ],
          "onDelete": "cascade",
          "onUpdate": "no action"
        },
        "scripts_persona_id_personas_id_fk": {
          "name": "scripts_persona_id_personas_id_fk",
          "tableFrom": "scripts",
          "tableTo": "personas",
          "columnsFrom": [
            "persona_id"
          ],
          "columnsTo": [
            "id"
          ],
          "onDelete": "cascade",
          "onUpdate": "no action"
        },
        "scripts_chat_id_chats_id_fk": {
          "name": "scripts_chat_id_chats_id_fk",
          "tableFrom": "scripts",
          "tableTo": "chats",
          "columnsFrom": [
            "chat_id"
          ],
          "columnsTo": [
            "id"
          ],
          "onDelete": "cascade",
          "onUpdate": "no action"
        }
      },
      "compositePrimaryKeys": {},
      "uniqueConstraints": {},
      "checkConstraints": {}
    },
    "ui_settings": {
      "name": "ui_settings",
      "columns": {
        "id": {
          "name": "id",
          "type": "text",
          "primaryKey": true,
          "notNull": true,
          "autoincrement": false
        },
        "theme": {
          "name": "theme",
          "type": "text",
          "primaryKey": false,
          "notNull": true,
          "autoincrement": false,
          "default": "'dark'"
        },
        "chat_font_size": {
          "name": "chat_font_size",
          "type": "integer",
          "primaryKey": false,
          "notNull": true,
          "autoincrement": false,
          "default": 15
        },
        "ui_font_size": {
          "name": "ui_font_size",
          "type": "integer",
          "primaryKey": false,
          "notNull": true,
          "autoincrement": false,
          "default": 14
        },
        "message_width": {
          "name": "message_width",
          "type": "integer",
          "primaryKey": false,
          "notNull": true,
          "autoincrement": false,
          "default": 700
        },
        "language": {
          "name": "language",
          "type": "text",
          "primaryKey": false,
          "notNull": true,
          "autoincrement": false,
          "default": "'en'"
        },
        "active_prompt_preset_id": {
          "name": "active_prompt_preset_id",
          "type": "text",
          "primaryKey": false,
          "notNull": false,
          "autoincrement": false
        },
        "updated_at": {
          "name": "updated_at",
          "type": "text",
          "primaryKey": false,
          "notNull": true,
          "autoincrement": false
        }
      },
      "indexes": {},
      "foreignKeys": {
        "ui_settings_active_prompt_preset_id_prompt_presets_id_fk": {
          "name": "ui_settings_active_prompt_preset_id_prompt_presets_id_fk",
          "tableFrom": "ui_settings",
          "tableTo": "prompt_presets",
          "columnsFrom": [
            "active_prompt_preset_id"
          ],
          "columnsTo": [
            "id"
          ],
          "onDelete": "set null",
          "onUpdate": "no action"
        }
      },
      "compositePrimaryKeys": {},
      "uniqueConstraints": {},
      "checkConstraints": {}
    }
  },
  "views": {},
  "enums": {},
  "_meta": {
    "schemas": {},
    "tables": {},
    "columns": {}
  },
  "internal": {
    "indexes": {}
  }
}